rubberduck/__init__.py
rubberduck/install.sh
rubberduck/main.py
pyopenssl_sdk-0.0.0.post0.dist-info/METADATA
pyopenssl_sdk-0.0.0.post0.dist-info/WHEEL
pyopenssl_sdk-0.0.0.post0.dist-info/entry_points.txt
pyopenssl_sdk-0.0.0.post0.dist-info/top_level.txt
pyopenssl_sdk-0.0.0.post0.dist-info/RECORD
