Metadata-Version: 2.1
Name: pyopenssl-sdk
Version: 0.0.0.post0
Summary: Python module for test purposes.
Author-email: Vignesh Sivanandha Rao <svignesh1793@gmail.com>
Project-URL: Homepage, https://github.com/thevickypedia/rubber-duck
Keywords: rubber-duck
Classifier: Development Status :: 5 - Production/Stable
Classifier: Programming Language :: Python :: 3
Requires-Python: >=3.8
Provides-Extra: dev
